robotframework_obfuscator/__init__.py
robotframework_obfuscator/__main__.py
robotframework_obfuscator/ast_to_code.py
robotframework_obfuscator/extract_var_name.py
robotframework_obfuscator/name_generator.py
robotframework_obfuscator/obfuscator.py
robotframework_obfuscator/obfuscator_transformer.py
robotframework_obfuscator-0.0.1.dist-info/LICENSE
robotframework_obfuscator-0.0.1.dist-info/METADATA
robotframework_obfuscator-0.0.1.dist-info/WHEEL
robotframework_obfuscator-0.0.1.dist-info/entry_points.txt
robotframework_obfuscator-0.0.1.dist-info/top_level.txt
robotframework_obfuscator-0.0.1.dist-info/RECORD
