Metadata-Version: 2.1
Name: robotframework-obfuscator
Version: 0.0.1
Summary: An obfuscator for Robot Framework code
Home-page: https://github.com/robocorp/robotframework-obfuscator
Author: Fabio Zadrozny
License: Apache-2.0
Platform: UNKNOWN
Classifier: Development Status :: 3 - Alpha
Classifier: Environment :: Console
Classifier: Intended Audience :: Developers
Classifier: License :: OSI Approved :: Apache Software License
Classifier: Operating System :: MacOS :: MacOS X
Classifier: Operating System :: Microsoft :: Windows
Classifier: Operating System :: POSIX
Classifier: Programming Language :: Python
Classifier: Programming Language :: Python :: 3.7
Classifier: Programming Language :: Python :: 3.8
Classifier: Programming Language :: Python :: 3.9
Classifier: Topic :: Text Editors
Classifier: Topic :: Text Editors :: Integrated Development Environments (IDE)
Classifier: Topic :: Software Development :: Debuggers
Classifier: Framework :: Robot Framework
Classifier: Framework :: Robot Framework :: Tool
Requires-Python: >=3.7
License-File: LICENSE
Requires-Dist: robotframework (>=3.2)
Requires-Dist: robotframework-lsp (>=0.29)
Provides-Extra: test
Requires-Dist: pytest ; extra == 'test'
Requires-Dist: pytest-xdist ; extra == 'test'
